uamconfig/__init__.py
uamconfig/cli.py
uamconfig/commands/__init__.py
uamconfig/commands/diff.py
uamconfig/commands/patch.py
uamconfig/utils/ConfigReader.py
uamconfig/utils/ConfigWriter.py
uamconfig/utils/__init__.py
uamconfig/utils/utils.py
uamconfig_cli-1.1.1.dist-info/DESCRIPTION.rst
uamconfig_cli-1.1.1.dist-info/METADATA
uamconfig_cli-1.1.1.dist-info/RECORD
uamconfig_cli-1.1.1.dist-info/WHEEL
uamconfig_cli-1.1.1.dist-info/entry_points.txt
uamconfig_cli-1.1.1.dist-info/metadata.json
uamconfig_cli-1.1.1.dist-info/top_level.txt
