Metadata-Version: 2.0
Name: uamconfig-cli
Version: 1.1.1
Summary: CLI utility for patching ADSelfService Plus config files following update
Home-page: http://github.com/simonmerrick/uamconfig
Author: Simon Merrick
Author-email: s.m3rrick@gmail.com
License: MIT
Keywords: ManageEngine ADSelfService Plus Configuration
Platform: UNKNOWN
Classifier: Development Status :: 5 - Production/Stable
Classifier: Intended Audience :: System Administrators
Classifier: Topic :: System :: Installation/Setup
Classifier: License :: OSI Approved :: MIT License
Classifier: Programming Language :: Python :: 3
Classifier: Programming Language :: Python :: 3.0
Classifier: Programming Language :: Python :: 3.1
Classifier: Programming Language :: Python :: 3.2
Classifier: Programming Language :: Python :: 3.3
Classifier: Programming Language :: Python :: 3.4
Classifier: Programming Language :: Python :: 3.5
Classifier: Programming Language :: Python :: 3.6
Requires-Dist: click
